mozreport/__init__.py
mozreport/_version.py
mozreport/cli.py
mozreport/databricks.py
mozreport/experiment.py
mozreport/template.py
mozreport/util.py
mozreport/etl_template/etl_script.py
mozreport/templates/rmarkdown/build.py
mozreport/templates/rmarkdown/report.Rmd
mozreport/tests/__init__.py
mozreport/tests/conftest.py
mozreport/tests/test_cli.py
mozreport/tests/test_databricks.py
mozreport/tests/test_experiment.py
mozreport/tests/test_template.py
mozreport/tests/test_util.py
mozreport-18.12.0.dist-info/LICENSE
mozreport-18.12.0.dist-info/METADATA
mozreport-18.12.0.dist-info/WHEEL
mozreport-18.12.0.dist-info/entry_points.txt
mozreport-18.12.0.dist-info/top_level.txt
mozreport-18.12.0.dist-info/RECORD
