Metadata-Version: 2.1
Name: mozreport
Version: 18.12.0
Summary: CLI for generating experiment reports
Home-page: https://github.com/mozilla/mozreport
Author: Tim D. Smith
Author-email: tdsmith@mozilla.com
License: UNKNOWN
Platform: UNKNOWN
Requires-Python: >=3.6
Requires-Dist: appdirs
Requires-Dist: attrs
Requires-Dist: cattrs
Requires-Dist: click
Requires-Dist: incremental
Requires-Dist: requests
Requires-Dist: toml
Provides-Extra: testing
Requires-Dist: coverage; extra == 'testing'
Requires-Dist: pytest-cov; extra == 'testing'
Requires-Dist: pytest; extra == 'testing'
